anzo_api/__init__.py
anzo_api/acl_api.py
anzo_api/anzo_api.py
anzo_api/anzo_construct.py
anzo_api/anzo_statics.py
anzo_api/azg_api.py
anzo_api/dataset_api.py
anzo_api/du_api.py
anzo_api/exceptions.py
anzo_api/graphmart_api.py
anzo_api/launch_config_api.py
anzo_api/migration_package_api.py
anzo_api/model_api.py
anzo_api/models.py
anzo_api/rest_adapter.py
anzo_api/utils.py
anzo_api/tests/__init__.py
anzo_api/tests/test_acl_api.py
anzo_api/tests/test_azg_api.py
anzo_api/tests/test_dataset_api.py
anzo_api/tests/test_graphmart_api.py
anzo_api/tests/test_launch_config_api.py
anzo_api/tests/test_migration_package_api.py
anzo_api/tests/test_model_api.py
anzo_api/tests/test_rest_adapter.py
anzo_api/tests/test_utils/233.ttl
anzo_api/tests/test_utils/ExamplePackage_20240320181221.zip
anzo_api/tests/test_utils/meshontology-ont.trig
anzo_api/tests/test_utils/test_common.py
anzo_api_wrapper-0.0.3.dist-info/METADATA
anzo_api_wrapper-0.0.3.dist-info/WHEEL
anzo_api_wrapper-0.0.3.dist-info/licenses/LICENSE
anzo_api_wrapper-0.0.3.dist-info/RECORD
