Metadata-Version: 2.3
Name: anzo-api-wrapper
Version: 0.0.3
Summary: A package for making Anzo API requests using Python
Author-email: Will Ades <wades@altair.com>
License-File: LICENSE
Classifier: Intended Audience :: Developers
Classifier: Natural Language :: English
Classifier: Programming Language :: Python :: 3
Classifier: Programming Language :: Python :: 3.5
Classifier: Programming Language :: Python :: 3.6
Classifier: Programming Language :: Python :: 3.7
Classifier: Programming Language :: Python :: 3.8
Classifier: Programming Language :: Python :: 3.9
Classifier: Programming Language :: Python :: 3.10
Requires-Python: >=3.5
Requires-Dist: requests==2.31.0
